gevent_psycopg2
