Metadata-Version: 1.0
Name: gevent-psycopg2
Version: 0.0.3
Summary: pip-installable package for patching psycopg2 to use gevent
Home-page: http://github.com/zacharyvoase/gevent-psycopg2
Author: Zachary Voase
Author-email: z@dvxhouse.com
License: UNKNOWN
Platform: UNKNOWN
